{"contestant": {"id": "278e5992983286a92e965ae13c227161", "username": null, "first_name": "Martino", "last_name": "Echerle"}, "num_medals": {"gold": 0, "silver": 0, "bronze": 0}, "best_rank": 43, "participations": [{"year": 2014, "internationals": [], "medal": null, "rank": 43, "region": "VEN", "scores": [{"task": "accensione", "score": 49.0, "max_score_possible": 100.0}, {"task": "bottleneck", "score": 22.0, "max_score_possible": 100.0}, {"task": "taglialegna", "score": 9.0, "max_score_possible": 100.0}]}]}