{"contestant": {"id": "2b470ca4d056a221e81be1d7866e6c2b", "username": null, "first_name": "Federico", "last_name": "Glaudo"}, "num_medals": {"gold": 1, "silver": 0, "bronze": 0}, "best_rank": 1, "participations": [{"year": 2012, "internationals": [{"code": "IOI", "name": "International Olympiads in Informatics", "link": "https://ioinformatics.org/", "color": "#198722"}], "medal": "gold", "rank": 1, "region": "LAZ", "scores": [{"task": "fermata", "score": 100.0, "max_score_possible": 100.0}, {"task": "convoglio", "score": 100.0, "max_score_possible": 100.0}, {"task": "fontane", "score": 100.0, "max_score_possible": 100.0}]}]}