{"contestant": {"id": "2b9b25a574b34c34fddcf5fcde4cf859", "first_name": "Alessio", "last_name": "Guerrieri"}, "participations": [{"year": 2005, "ioi": true, "medal": "silver", "rank": 6, "region": "TRE", "scores": [{"task": "messaggi", "score": null, "max_score_possible": null}, {"task": "camelot", "score": null, "max_score_possible": null}, {"task": "pirellone", "score": null, "max_score_possible": null}]}, {"year": 2004, "ioi": false, "medal": "gold", "rank": 4, "region": "TRE", "scores": [{"task": "collage", "score": null, "max_score_possible": null}, {"task": "follie", "score": null, "max_score_possible": null}, {"task": "passaporti", "score": null, "max_score_possible": null}]}]}