{"contestant": {"id": "3d47e1c4fe086fbeb0b6596ae7e3e2a1", "username": null, "first_name": "Michele", "last_name": "Busi"}, "num_medals": {"gold": 0, "silver": 0, "bronze": 0}, "best_rank": 76, "participations": [{"year": 2010, "internationals": [], "medal": null, "rank": 76, "region": "EMI", "scores": [{"task": "baht", "score": 0.0, "max_score_possible": 20.0}, {"task": "fuga", "score": 0.0, "max_score_possible": 20.0}, {"task": "salti", "score": 0.0, "max_score_possible": 20.0}, {"task": "scuola", "score": 10.0, "max_score_possible": 20.0}]}]}