{"contestant": {"id": "6c4e009dc8612ef8d803aa83df1b12cd", "first_name": "Alessandro", "last_name": "Dovis"}, "participations": [{"year": 2009, "ioi": true, "medal": "silver", "rank": 13, "region": "PIE", "scores": [{"task": "amici", "score": 9.0, "max_score_possible": 20.0}, {"task": "numeri", "score": 3.0, "max_score_possible": 20.0}, {"task": "pesca", "score": 9.0, "max_score_possible": 20.0}]}, {"year": 2008, "ioi": false, "medal": null, "rank": 41, "region": "PIE", "scores": [{"task": "cnn", "score": 3.0, "max_score_possible": 20.0}, {"task": "triade", "score": 3.0, "max_score_possible": 20.0}, {"task": "parole", "score": 2.0, "max_score_possible": 20.0}]}]}