{"contestant": {"id": "92cacbdc31d25fede81f2d9123dee55d", "username": null, "first_name": "Federico", "last_name": "Moro"}, "num_medals": {"gold": 0, "silver": 0, "bronze": 0}, "best_rank": null, "participations": [{"year": 2004, "internationals": [], "medal": null, "rank": null, "region": "VEN", "scores": [{"task": "collage", "score": null, "max_score_possible": null}, {"task": "follie", "score": null, "max_score_possible": null}, {"task": "passaporti", "score": null, "max_score_possible": null}]}]}