{"contestant": {"id": "9d3e73047f014444682caa204d03259c", "username": null, "first_name": "Antonello", "last_name": "Contini"}, "num_medals": {"gold": 0, "silver": 0, "bronze": 0}, "best_rank": 62, "participations": [{"year": 2013, "internationals": [], "medal": null, "rank": 62, "region": "LOM", "scores": [{"task": "bufale", "score": 5.0, "max_score_possible": 100.0}, {"task": "spiedini", "score": 5.0, "max_score_possible": 100.0}, {"task": "maree", "score": 5.0, "max_score_possible": 100.0}]}]}